pyfred/__init__.py
pyfred/cli.py
pyfred/model.py
pyfred/workflow.py
pyfred/template/.gitignore
pyfred/template/requirements.txt
pyfred/template/workflow/workflow.py
pyfred_cli-0.1.6.dist-info/LICENSE
pyfred_cli-0.1.6.dist-info/METADATA
pyfred_cli-0.1.6.dist-info/WHEEL
pyfred_cli-0.1.6.dist-info/entry_points.txt
pyfred_cli-0.1.6.dist-info/top_level.txt
pyfred_cli-0.1.6.dist-info/RECORD
