Metadata-Version: 2.1
Name: pyfred-cli
Version: 0.1.6
Summary: Python helpers to build Alfred workflows
Author: Björn Marschollek
Project-URL: Source Code, https://github.com/muffix/pyfred-cli
Project-URL: Documentation, https://muffix.github.io/pyfred-cli
Classifier: Development Status :: 4 - Beta
Classifier: Programming Language :: Python :: 3.9
Classifier: Topic :: Software Development :: Libraries :: Python Modules
Classifier: Environment :: Console
Classifier: Operating System :: MacOS
Classifier: Intended Audience :: Developers
License-File: LICENSE
Provides-Extra: doc
Provides-Extra: test
